ame/__init__.py
ame/__main__.py
ame/constantes.py
ame/ploter.py
ame/analise/__init__.py
ame/analise/geometria/__init__.py
ame/analise/geometria/ponto.py
ame/analise/sistema/__init__.py
ame/analise/sistema/apoios.py
ame/analise/sistema/cargas.py
ame/analise/sistema/elemento_numerado.py
ame/analise/sistema/elementos.py
ame/analise/sistema/estrutura.py
ame/analise/sistema/material.py
ame/analise/sistema/no.py
ame/analise/sistema/secao.py
ame/tests/__init__.py
ame/tests/exemplos/__init__.py
ame/tests/exemplos/dados_exemplos.py
ame/tests/exemplos/e1.ame
ame/tests/exemplos/e1.ftl
ame/tests/exemplos/e2.ame
ame/tests/exemplos/e2.ftl
ame/tests/test_analise/__init__.py
ame/tests/test_analise/test_geometria/__init__.py
ame/tests/test_analise/test_geometria/test_ponto/__init__.py
ame/tests/test_analise/test_geometria/test_ponto/test_ponto.py
ame/tests/test_analise/test_sistema/__init__.py
ame/tests/test_analise/test_sistema/test_elemento_numerado.py
ame/tests/test_analise/test_sistema/test_apoio/__init__.py
ame/tests/test_analise/test_sistema/test_apoio/test_apoios.py
ame/tests/test_analise/test_sistema/test_cargas/__init__.py
ame/tests/test_analise/test_sistema/test_cargas/test_cargas.py
ame/tests/test_analise/test_sistema/test_elementos/__init__.py
ame/tests/test_analise/test_sistema/test_elementos/test_elementos.py
ame/tests/test_analise/test_sistema/test_estrutura/__init__.py
ame/tests/test_analise/test_sistema/test_estrutura/test_estrutura.py
ame/tests/test_analise/test_sistema/test_material/__init__.py
ame/tests/test_analise/test_sistema/test_material/test_material.py
ame/tests/test_analise/test_sistema/test_no/__init__.py
ame/tests/test_analise/test_sistema/test_no/test_no.py
ame/tests/test_analise/test_sistema/test_secao/__init__.py
ame/tests/test_analise/test_sistema/test_secao/test_secao.py
ame-0.0.2.dist-info/LICENSE.md
ame-0.0.2.dist-info/METADATA
ame-0.0.2.dist-info/WHEEL
ame-0.0.2.dist-info/top_level.txt
ame-0.0.2.dist-info/RECORD
