Metadata-Version: 2.1
Name: ame
Version: 0.0.2
Summary: Biblioteca para análise matricial de estruturas planas pelo método dos deslocamentos.
Home-page: https://github.com/lorranfoliveira/ame
Author: Lorran Ferreira Oliveira
Author-email: lorranfoliveira@gmail.com
License: MIT
Platform: UNKNOWN
Classifier: License :: OSI Approved :: MIT License
Classifier: Programming Language :: Python :: 3.7
Classifier: Operating System :: OS Independent
Requires-Dist: numpy (>=1.17.2)
Requires-Dist: scipy (>=1.3.1)
Requires-Dist: PTable (>=0.9.2)
Requires-Dist: matplotlib (>=3.1.1)
